sugaroid/__init__.py
sugaroid/__main__.py
sugaroid/sugaroid.py
sugaroid/train.py
sugaroid/version.py
sugaroid/backend/__init__.py
sugaroid/backend/sql.py
sugaroid/brain/__init__.py
sugaroid/brain/about.py
sugaroid/brain/aki.py
sugaroid/brain/areyou.py
sugaroid/brain/assertive.py
sugaroid/brain/because.py
sugaroid/brain/brain.py
sugaroid/brain/bye.py
sugaroid/brain/canmay.py
sugaroid/brain/constants.py
sugaroid/brain/convert.py
sugaroid/brain/covid.py
sugaroid/brain/debug.py
sugaroid/brain/dis.py
sugaroid/brain/do.py
sugaroid/brain/dolike.py
sugaroid/brain/either.py
sugaroid/brain/emotion.py
sugaroid/brain/feel.py
sugaroid/brain/fun.py
sugaroid/brain/hangman.py
sugaroid/brain/iam.py
sugaroid/brain/idk.py
sugaroid/brain/imitate.py
sugaroid/brain/interrupt.py
sugaroid/brain/joke.py
sugaroid/brain/learn.py
sugaroid/brain/let.py
sugaroid/brain/myname.py
sugaroid/brain/news.py
sugaroid/brain/ok.py
sugaroid/brain/oneword.py
sugaroid/brain/ooo.py
sugaroid/brain/play.py
sugaroid/brain/postprocessor.py
sugaroid/brain/preprocessors.py
sugaroid/brain/reader.py
sugaroid/brain/rereversei.py
sugaroid/brain/reset.py
sugaroid/brain/reset_trivia.py
sugaroid/brain/reversethink.py
sugaroid/brain/time.py
sugaroid/brain/trivia.py
sugaroid/brain/twoword.py
sugaroid/brain/update.py
sugaroid/brain/utils.py
sugaroid/brain/waitwhat.py
sugaroid/brain/whatamidoing.py
sugaroid/brain/whatwhat.py
sugaroid/brain/whoami.py
sugaroid/brain/why.py
sugaroid/brain/wiki.py
sugaroid/brain/yesno.py
sugaroid/cli/__init__.py
sugaroid/cli/cli.py
sugaroid/config/__init__.py
sugaroid/config/config.py
sugaroid/data/sugaroid.db
sugaroid/game/__init__.py
sugaroid/game/game.py
sugaroid/google/__init__.py
sugaroid/google/google.py
sugaroid/gui/__init__.py
sugaroid/gui/ux.py
sugaroid/gui/ui/main.py
sugaroid/gui/ui/main.ui
sugaroid/gui/ui/rsrc.qrc
sugaroid/gui/ui/rsrc_rc.py
sugaroid/gui/ui/send.png
sugaroid/gui/ui/sugaroid.png
sugaroid/gui/ui/sugaroid_adorable.png
sugaroid/gui/ui/sugaroid_all.png
sugaroid-0.11.5.dist-info/LICENSE
sugaroid-0.11.5.dist-info/METADATA
sugaroid-0.11.5.dist-info/WHEEL
sugaroid-0.11.5.dist-info/entry_points.txt
sugaroid-0.11.5.dist-info/top_level.txt
sugaroid-0.11.5.dist-info/RECORD
