Metadata-Version: 2.1
Name: sugaroid
Version: 0.11.5
Summary: Open Source Natural Language Processing Bot.
Home-page: https://srevinsaju.github.io/sugaroid
Author: srevinsaju
Author-email: srevin03@gmail.com
License: MIT
Download-URL: https://github.com/srevinsaju/sugaroid/archive/master.zip
Platform: UNKNOWN
Classifier: Operating System :: OS Independent
Classifier: Programming Language :: Python :: 3.7
Classifier: Programming Language :: Python :: 3.6
Classifier: Programming Language :: Python :: 3.8
Classifier: Operating System :: MacOS :: MacOS X
Classifier: Operating System :: Microsoft :: Windows
Classifier: Operating System :: POSIX
Classifier: License :: OSI Approved :: GNU General Public License v3 (GPLv3)
Requires-Dist: googletrans
Requires-Dist: google
Requires-Dist: Django
Requires-Dist: pyjokes
Requires-Dist: scikit-learn
Requires-Dist: nltk
Requires-Dist: lxml
Requires-Dist: pyinflect
Requires-Dist: newsapi-python
Requires-Dist: wikipedia-API
Requires-Dist: pyspellchecker
Requires-Dist: python-dotenv
Requires-Dist: psutil
Requires-Dist: emoji
Requires-Dist: akinator.py
Requires-Dist: CurrencyConverter
Requires-Dist: colorama
